tali/__init__.py
tali/cli.py
tali/common.py
tali/config.yaml
tali/book/__init__.py
tali/book/book.py
tali/book/history.py
tali/book/item.py
tali/book/result.py
tali/book/select.py
tali/parser/__init__.py
tali/parser/command.grammar
tali/parser/command.py
tali/parser/common.py
tali/parser/datetime.grammar
tali/parser/datetime.py
tali/parser/editor.py
tali/render/__init__.py
tali/render/cheatsheet.py
tali/render/cli.py
tali/render/common.py
tali_cli-0.2.4.dist-info/licenses/LICENSE
tali_cli-0.2.4.dist-info/METADATA
tali_cli-0.2.4.dist-info/WHEEL
tali_cli-0.2.4.dist-info/entry_points.txt
tali_cli-0.2.4.dist-info/top_level.txt
tali_cli-0.2.4.dist-info/RECORD
