Metadata-Version: 2.4
Name: tali-cli
Version: 0.2.4
Summary: tali • The CLI magic for task alchemists • Weave productivity spells with symbols that conjures order from chaos.
Author: admk
License-Expression: MIT
Project-URL: Homepage, https://github.com/admk/tali
Project-URL: Issues, https://github.com/admk/tali/issues
Keywords: cli,task,todo,productivity
Classifier: Development Status :: 3 - Alpha
Classifier: Environment :: Console
Classifier: Programming Language :: Python :: 3
Classifier: Topic :: Utilities
Requires-Python: >=3.10
License-File: LICENSE
Requires-Dist: GitPython>=3.1
Requires-Dist: PyYAML>=6.0
Requires-Dist: parsimonious>=0.10
Requires-Dist: python-box>=7.0
Requires-Dist: python-dateutil>=2.8
Requires-Dist: rich-argparse>=1.7
Requires-Dist: rich>=12.5
Dynamic: license-file
